LICENSE
README.md
setup.py
filewarmer/__init__.py
filewarmer/filewarmer.py
filewarmer.egg-info/PKG-INFO
filewarmer.egg-info/SOURCES.txt
filewarmer.egg-info/dependency_links.txt
filewarmer.egg-info/top_level.txt
filewarmer/lib/file_warmer_linux_amd64.h
filewarmer/lib/file_warmer_linux_amd64.so
filewarmer/lib/file_warmer_linux_arm64.h
filewarmer/lib/file_warmer_linux_arm64.so